{
    "Bankfiles" : 
    [
        {
            "BankDescription": "BGM",
            "BankName": "Content/Sound/Master.bank",
            "BankStringName": "Content/Sound/Master.strings.bank",
            "Events":[
              {
                "EventName": "FirstEvent",
                "SongId": 0

              },
              {
                "EventName": "TitleScreenMusic",
                "SongId": 1 
              }

            ]
        },
        {
            "BankDescription": "SFX",
            "BankName": "Content/Sound/Master.bank",
            "BankStringName": "Content/Sound/Master.strings.bank",
            "Events":[
                {
                    "EventName":"FirstEvent",
                    "SongId":0

                }
            ]
        }

    ]

}
